rcb4/__init__.py
rcb4/_lazy_imports.py
rcb4/armh7interface.py
rcb4/asm.py
rcb4/ctype_utils.py
rcb4/ics.py
rcb4/rcb4interface.py
rcb4/struct_header.py
rcb4/temperature.py
rcb4/units.py
rcb4/usb_utils.py
rcb4/apps/__init__.py
rcb4/apps/armh7_tool.py
rcb4/apps/ics_manager.py
rcb4/apps/write_firmware.py
rcb4/data/__init__.py
rcb4-0.1.3.dist-info/licenses/LICENSE
rcb4-0.1.3.dist-info/METADATA
rcb4-0.1.3.dist-info/WHEEL
rcb4-0.1.3.dist-info/entry_points.txt
rcb4-0.1.3.dist-info/top_level.txt
rcb4-0.1.3.dist-info/RECORD
