Metadata-Version: 2.4
Name: rcb4
Version: 0.1.3
Summary: A python library for RCB4
Home-page: https://github.com/iory/rcb4
Author: Iori Yanokura
Author-email: yanokura@jsk.imi.i.u-tokyo.ac.jp
License: MIT
Classifier: Development Status :: 5 - Production/Stable
Classifier: Intended Audience :: Developers
Classifier: Natural Language :: English
Classifier: License :: OSI Approved :: MIT License
Classifier: Programming Language :: Python
Classifier: Programming Language :: Python :: 2.7
Classifier: Programming Language :: Python :: 3.5
Classifier: Programming Language :: Python :: 3.6
Classifier: Programming Language :: Python :: 3.7
Classifier: Programming Language :: Python :: Implementation :: CPython
License-File: LICENSE
Requires-Dist: colorama
Requires-Dist: cstruct
Requires-Dist: gdown
Requires-Dist: libusb1
Requires-Dist: numpy>=1.22.0
Requires-Dist: pandas
Requires-Dist: pyelftools
Requires-Dist: pyserial
Requires-Dist: pyyaml
Requires-Dist: readchar
Requires-Dist: setuptools; python_version >= "3.12"
Requires-Dist: pyftdi; sys_platform == "darwin"
Requires-Dist: tabulate
Dynamic: author
Dynamic: author-email
Dynamic: classifier
Dynamic: description
Dynamic: description-content-type
Dynamic: home-page
Dynamic: license
Dynamic: license-file
Dynamic: requires-dist
Dynamic: summary
